Jenkinsfile
LICENSE.txt
MANIFEST.in
README.md
build.parameters
ledgerhelpers.spec
pyproject.toml
setup.cfg
tox.ini
applications/addtrans.desktop
applications/cleartrans-cli.desktop
applications/sellstock-cli.desktop
applications/sorttrans-cli.desktop
applications/updateprices.desktop
applications/withdraw-cli.desktop
bin/addtrans
bin/cleartrans-cli
bin/sellstock-cli
bin/sorttrans-cli
bin/updateprices
bin/withdraw-cli
doc/addtrans-account.png
doc/addtrans-amount.png
doc/addtrans-dropdown.png
doc/addtrans-readyagain.png
doc/addtrans-started-up.png
doc/addtrans.md
man/addtrans.1
man/cleartrans-cli.1
man/sellstock-cli.1
man/sorttrans-cli.1
man/withdraw-cli.1
src/ledgerhelpers/__init__.py
src/ledgerhelpers/dateentry.py
src/ledgerhelpers/diffing.py
src/ledgerhelpers/editabletransactionview.py
src/ledgerhelpers/gui.py
src/ledgerhelpers/journal.py
src/ledgerhelpers/legacy.py
src/ledgerhelpers/legacy_needsledger.py
src/ledgerhelpers/parser.py
src/ledgerhelpers/transactionstatebutton.py
src/ledgerhelpers.egg-info/PKG-INFO
src/ledgerhelpers.egg-info/SOURCES.txt
src/ledgerhelpers.egg-info/dependency_links.txt
src/ledgerhelpers.egg-info/requires.txt
src/ledgerhelpers.egg-info/top_level.txt
src/ledgerhelpers/programs/__init__.py
src/ledgerhelpers/programs/addtrans.py
src/ledgerhelpers/programs/cleartranscli.py
src/ledgerhelpers/programs/common.py
src/ledgerhelpers/programs/sellstockcli.py
src/ledgerhelpers/programs/sorttranscli.py
src/ledgerhelpers/programs/updateprices.py
src/ledgerhelpers/programs/withdrawcli.py
tests/__init__.py
tests/test_base.py
tests/test_ledgerhelpers.py
tests/test_parser.py
tests/dogtail/addtrans.py
tests/testdata/no_end_value.dat
tests/testdata/simple_transaction.dat
tests/testdata/with_comments.dat
tests/testdata/zero.dat