Metadata-Version: 2.1
Name: ledgerhelpers
Version: 0.3.10
Summary: A collection of helper programs and a helper library for Ledger (ledger-cli)
Home-page: https://github.com/Rudd-O/ledgerhelpers
Author: Manuel Amador (Rudd-O)
Author-email: rudd-o@rudd-o.com
License: GPLv2+
Classifier: Development Status :: 4 - Beta
Classifier: Environment :: X11 Applications :: GTK
Classifier: Intended Audience :: End Users/Desktop
Classifier: License :: OSI Approved :: GNU General Public License v2 or later (GPLv2+)
Classifier: Operating System :: POSIX :: Linux
Classifier: Programming Language :: Python :: 3 :: Only
Classifier: Programming Language :: Python :: 3.6
Classifier: Topic :: Office/Business :: Financial :: Accounting
License-File: LICENSE.txt
